README
safebrowsinglookup.py
setup.py
Google_Safe_Browsing_v2_Lookup.egg-info/PKG-INFO
Google_Safe_Browsing_v2_Lookup.egg-info/SOURCES.txt
Google_Safe_Browsing_v2_Lookup.egg-info/dependency_links.txt
Google_Safe_Browsing_v2_Lookup.egg-info/namespace_packages.txt
Google_Safe_Browsing_v2_Lookup.egg-info/top_level.txt
tests/__init__.py
tests/test_safebrowsinglookup.py