Metadata-Version: 1.0
Name: Google-Safe-Browsing-v2-Lookup
Version: 0.2.2
Summary: Client to interact with the Google Safe Browsing v3 Lookup API
Home-page: https://github.com/juliensobrier/google-safe-browsing-lookup-python
Author: Julien Sobrier
Author-email: julien@sobrier.net
License: Apache
Platform: UNKNOWN
Classifier: Development Status :: 4 - Beta
Classifier: Environment :: Console
Classifier: Intended Audience :: Developers
Classifier: Intended Audience :: Information Technology
Classifier: License :: OSI Approved :: BSD License
Classifier: Operating System :: OS Independent
Classifier: Programming Language :: Python
